{"status":"ok","data":[{"id":"1182","name":"Bacau - Piata Sfanta Vineri","geometry":"wm}mGkxb~CqAOiCHkDHoDB}FAgD@{ADeGuBaCkAqCcBqGoD_EuBgBcAoGwDaAo@yCkBcBkA{BiBu@k@_@y@k@gC}@mDMo@aB|AwD`DmAiCmB}AqAcAeCqB_E{CyD{BwCkBmBcBkAsAw@sAeBgDcB}CyEtIq@eD_AwFU}@yF{MqFwMgAmC_BsDoEsK}CoHuE}KoEgKqCcHSIs@}AMQF{BHgDd@u@Hs@Ou@Wi@H}Hb@wRLqKPiMkCMgCIi@?oAV{DlA}Ab@u@HoCMuBKaCCc@HG`AL`@v@|AzAfDnA`Dr@nBnAdDhArD","color":"2F91C9","direction":"0","duration":"00:25","stops":[{"id":"11566","name":"Bacau","latitude":"44.3928154578","longitude":"26.0696406257"},{"id":"11591","name":"Complex Comercial","latitude":"44.3969478856","longitude":"26.0699067008"},{"id":"11569","name":"Amurgului","latitude":"44.4008565771","longitude":"26.0714645279"},{"id":"11570","name":"Pecineaga","latitude":"44.4036696922","longitude":"26.0732669724"},{"id":"11571","name":"Fabrica de Paine","latitude":"44.4052409919","longitude":"26.0742647541"},{"id":"11572","name":"Calea Ferentari","latitude":"44.4087436886","longitude":"26.0777194393"},{"id":"11573","name":"Doina","latitude":"44.4111272418","longitude":"26.0783631695"},{"id":"11574","name":"Soseaua Progresului","latitude":"44.41437","longitude":"26.08091"},{"id":"11575","name":"Soseaua Viilor","latitude":"44.41685","longitude":"26.08357"},{"id":"11576","name":"Piata Chirigiu","latitude":"44.4179","longitude":"26.083"},{"id":"11577","name":"Piata Regina Maria","latitude":"44.42105","longitude":"26.09025"},{"id":"11578","name":"11 iunie","latitude":"44.4234649839","longitude":"26.0944564236"},{"id":"11579","name":"Piata Unirii","latitude":"44.4266","longitude":"26.10047"},{"id":"11401","name":"I.C.Bratianu","latitude":"44.4265880887","longitude":"26.1046466721"},{"id":"11564","name":"Mircea Voda","latitude":"44.4270202226","longitude":"26.1120946301"},{"id":"11565","name":"Matei Basarab","latitude":"44.4309736393","longitude":"26.1115581882"},{"id":"11521","name":"Piata Sfanta Vineri","latitude":"44.4300006332","longitude":"26.10647272"}]},{"id":"1181","name":"Piata Sfanta Vineri - Bacau","geometry":"cm}mGcvb~CwCzQU|@iAy@sFeEkHgFkBuA{DoC[GoJwDqAs@mDwBqGkDcCqA{D_CsCcBqCaBcD{B_E}Cg@sA}A}GeFfEs@l@_BoDsBaBsIyGqAcAaDkBsCiBuBkBoAyAeE}Hq@gAyClFcAbBi@qCsAmH}@aCgHwPcG_OoA}CoFkMwCaHwAuDiDyHuEwKk@uAMKaAkBBeBgDSgESQAuAeCZ_HJmAAoAcEeO","color":"2F91C9","direction":"1","duration":"00:25","stops":[{"id":"11521","name":"Piata Sfanta Vineri","latitude":"44.4300006332","longitude":"26.10647272"},{"id":"11400","name":"Piata Unirii 1","latitude":"44.42758","longitude":"26.10096"},{"id":"11580","name":"11 Iunie","latitude":"44.42433","longitude":"26.09583"},{"id":"11581","name":"Piata Regina Maria","latitude":"44.4219","longitude":"26.09113"},{"id":"11582","name":"Piata Chirigiu","latitude":"44.41736","longitude":"26.08248"},{"id":"11583","name":"Soseaua Viilor","latitude":"44.41643","longitude":"26.08334"},{"id":"11584","name":"Soseaua Progresul","latitude":"44.4136494106","longitude":"26.0801312816"},{"id":"11585","name":"Doina","latitude":"44.4107064866","longitude":"26.0778567684"},{"id":"11586","name":"Nasaud","latitude":"44.4094035823467","longitude":"26.0767726195335"},{"id":"11587","name":"Calea Ferentari","latitude":"44.4077787434","longitude":"26.076376189"},{"id":"11588","name":"Fabrica de Paine","latitude":"44.4050807979","longitude":"26.0738978279"},{"id":"11589","name":"Pecineaga","latitude":"44.4033868538","longitude":"26.0728142154"},{"id":"11590","name":"Amurgului","latitude":"44.4004894058","longitude":"26.0709903133"},{"id":"11568","name":"Complex Comercial","latitude":"44.3970774385","longitude":"26.0692651165"},{"id":"11567","name":"Soseaua Salaj","latitude":"44.3939190259","longitude":"26.0666472805"},{"id":"11566","name":"Bacau","latitude":"44.3928154578","longitude":"26.0696406257"}]}]}