{"status":"ok","data":[{"id":"1642","name":"Cartier Damaroaia - Piata Romana","geometry":"ebpnGoa_~CA?K}BDs@ZI`CYhAO??dCYvEm@f@OjAQc@mIa@cI??[_GHcAFKPWb@c@lBiBtDkD~@mAb@q@f@eAp@yBfDwLzO}k@fCeJNUNOVKNSfAcALKl@WxAk@??px@y[ZEf@@VCNOJW@UAWQcCp@_L??pB{ZHc@h@mANSL_@Bg@RwAdGmOxAsDfAaCR[??jAiBj@u@l@s@hBaBrBwAtE{ChBmA??xQmK~D}BhBeAtB}@jFoBvCgAp@M|AO|Fk@pKeAv@EbB?`E@P?TEh@OzCk@f@G??d@KJBRE~@r@x@|@dD~DqIbDeA`@","color":"2F91C9","direction":"0","duration":"00:28","stops":[{"id":"14202","name":"Cartier Damaroaia","latitude":"44.48814","longitude":"26.05104"},{"id":"11505","name":"Dridu","latitude":"44.48503","longitude":"26.05642"},{"id":"11916","name":"Hotel Parc","latitude":"44.4820727465","longitude":"26.0619995487"},{"id":"11917","name":"City Center","latitude":"44.4805264767","longitude":"26.065904845"},{"id":"11918","name":"Casa Presei","latitude":"44.4792404389","longitude":"26.0693380726"},{"id":"11919","name":"Piata Presei","latitude":"44.4784289957","longitude":"26.0714409245"},{"id":"11733","name":"Muzeul Satului","latitude":"44.471830625","longitude":"26.0755607975"},{"id":"11734","name":"Arcul de Triumf","latitude":"44.4669305515","longitude":"26.0794124496"},{"id":"11735","name":"Piata Charles de Gaulle","latitude":"44.4653149684","longitude":"26.0874912632"},{"id":"11736","name":"Piata Dorobantilor","latitude":"44.4597557957","longitude":"26.0944757355"},{"id":"11737","name":"Liceul I.L. Caragiale","latitude":"44.4572670138","longitude":"26.0961387051"},{"id":"11738","name":"Soseaua Stefan cel Mare","latitude":"44.45391","longitude":"26.09804"},{"id":"11739","name":"A.S.E.","latitude":"44.44774","longitude":"26.09933"},{"id":"14197","name":"Piata Lahovari","latitude":"44.4454","longitude":"26.0997"},{"id":"11717","name":"Piata Romana","latitude":"44.44621","longitude":"26.09731"}]},{"id":"1643","name":"Piata Romana - Cartier Damaroaia","geometry":"gzgnG}bh~CAAoCdAKSMKIsAA{E@sADmA?OWFi@BuE@??gA?w@BgIv@uEd@yEb@??m@Be@LaBj@gDtAqDtAiCxAyEnCyL|GsEhC{@f@}EbD??kDpCcAhAc@l@y@lAqA~BwFjNuBnFUZWLo@NI@]NMRMb@Aj@`@vBBr@e@zH??{Bh^K^gBnCo[hMwHzC??uUjJYHWD_AB[AUJORI\\?b@FZGbAuB|HeFbR??{Iv[yCvKg@tAo@pAq@bA_B~AcB|AcD|CILMXF~AZ~Fr@fNThE??z@|P`@dH`@rHPhDh@|KVzELtDC^Al@IP??GJWOuI_PcM{UKk@]}H[}E","color":"2F91C9","direction":"1","duration":"00:28","stops":[{"id":"11717","name":"Piata Romana","latitude":"44.44621","longitude":"26.09731"},{"id":"16057","name":"A.S.E.","latitude":"44.44736","longitude":"26.09948"},{"id":"11718","name":"Perla","latitude":"44.4536676647","longitude":"26.0985097778"},{"id":"11719","name":"Liceul I.L.Caragiale","latitude":"44.458185961","longitude":"26.0957417381"},{"id":"11720","name":"Piata Dorobantilor","latitude":"44.4610192905","longitude":"26.0938427341"},{"id":"11721","name":"Piata Charles de Gaulle","latitude":"44.4652843408","longitude":"26.0881028069"},{"id":"11722","name":"Arcul de Triumf","latitude":"44.4676196492","longitude":"26.0784683121"},{"id":"11723","name":"Muzeul Satului","latitude":"44.4724584171","longitude":"26.0756895435"},{"id":"11921","name":"Piata Presei","latitude":"44.47862803","longitude":"26.0716984165"},{"id":"11922","name":"Casa Presei","latitude":"44.4796920863","longitude":"26.068919648"},{"id":"11923","name":"City Center","latitude":"44.4809781142","longitude":"26.0654113186"},{"id":"11924","name":"Hotel Parc","latitude":"44.4822717684","longitude":"26.0619459045"},{"id":"11488","name":"Jiului","latitude":"44.48493","longitude":"26.05825"},{"id":"11489","name":"Dridu","latitude":"44.48505","longitude":"26.05535"},{"id":"11490","name":"Depozit Pajura","latitude":"44.4842650113","longitude":"26.0477538002"},{"id":"14198","name":"Bulevardul Bucurestii Noi","latitude":"44.48363","longitude":"26.04189"},{"id":"14199","name":"Neatarnarii","latitude":"44.48561","longitude":"26.04415"},{"id":"14200","name":"Izbiceni","latitude":"44.48736","longitude":"26.04695"},{"id":"14201","name":"Cartier Damaroaia","latitude":"44.4881","longitude":"26.05064"}]}]}