{"status":"ok","data":[{"id":"1110","name":"Depou Militari - Gara Basarab","geometry":"stdnG_aq}CsJ}hCGkAAe@?S@OHUNMPMNExHgBEFlBdB|ChCjKvIbDdC`@Nh@Hl@CnCQtBUPQBK?WOaCYuFg@gNSoG??o@eRs@aVIiAKiAOq@}BqKsAoGQgAKkAe@{LmAm[_AmYO}EG{@q@sRKcD{@qQ_@kJO_GO_KSkLUiQCkEI{EWgGMmI[cME_CUGKEsAHiLP??wCDcGCwEEwEAiBOiBUmBy@iBiAwAwAmA}AqHuK_GoIu@eA_CSoDo@eCi@qBYsBa@m@Oo@Sk@Uk@]g@Yg@_@e@]c@e@aAmA]g@[i@s@wAq@}AgIuU","color":"901939","direction":"0","duration":"00:30","stops":[{"id":"10608","name":"Depou Militari","latitude":"44.42968","longitude":"25.97928"},{"id":"10609","name":"Inscut","latitude":"44.43005","longitude":"25.98347"},{"id":"10610","name":"S.C. Vest","latitude":"44.43057","longitude":"25.98971"},{"id":"10611","name":"Urbis","latitude":"44.43095","longitude":"25.99444"},{"id":"10612","name":"Cesarom","latitude":"44.43157","longitude":"26.00132"},{"id":"10613","name":"C.F.R. Cotroceni","latitude":"44.42858","longitude":"26.00182"},{"id":"10614","name":"Comautosport","latitude":"44.4237611343","longitude":"26.0006949795"},{"id":"10615","name":"Radox","latitude":"44.42425","longitude":"26.00658"},{"id":"10616","name":"Valea Oltului","latitude":"44.42483","longitude":"26.01291"},{"id":"10617","name":"Frigocom","latitude":"44.4261","longitude":"26.01799"},{"id":"10618","name":"Romancierilor","latitude":"44.42658","longitude":"26.02394"},{"id":"10619","name":"Compasului","latitude":"44.42698","longitude":"26.02893"},{"id":"10620","name":"Brasov","latitude":"44.4274","longitude":"26.03411"},{"id":"10621","name":"Sergent Moise","latitude":"44.42793","longitude":"26.04062"},{"id":"10622","name":"Sibiu","latitude":"44.4282430521","longitude":"26.0481915367"},{"id":"10623","name":"Bd. Vasile Milea","latitude":"44.42857","longitude":"26.05391"},{"id":"10476","name":"Bd. Iuliu Maniu","latitude":"44.4352","longitude":"26.05443"},{"id":"10477","name":"Pod Grozavesti","latitude":"44.44274","longitude":"26.06051"},{"id":"10668","name":"Calea Plevnei","latitude":"44.44744","longitude":"26.06342"},{"id":"10871","name":"Calea Giulesti","latitude":"44.448107","longitude":"26.0648534191"},{"id":"10873","name":"Gara Basarab","latitude":"44.4494086589","longitude":"26.0675248993"}]},{"id":"1109","name":"Gara Basarab - Depou Militari","geometry":"_qhnGsib~CHAHCPHnAbDfBxFzB~Fv@|B~@~Bx@hAbAjAf@b@d@b@tA|@h@Xh@TzAb@xDx@dCn@??~Bd@xAV^Pf@Lz@Zh@h@|DjFpC~D??`FdHfB~BxArA|@h@v@`@x@XjAZz@LvALd@FdCDz@CzBA|IB|HI|BEh@D|BI`@JLPHVF`C??RnJXvMH`DLbKPpKl@`^^lML`DJ`Bn@|ND`@h@zNx@zTd@lOTnFhAp[LtDHvBN|Af@xC|DrRb@jDNjCVbKJvC??vArb@t@`RD|@CLEFIBgGf@]A_@IWOyCcCkKyI{CgC{BwAmIpBKDIFIJEPCN?T?PBRbKtoCVlE","color":"901939","direction":"1","duration":"00:30","stops":[{"id":"10874","name":"Gara Basarab ","latitude":"44.4496077921","longitude":"26.0675785435"},{"id":"10872","name":"Calea Giulesti","latitude":"44.4480836396","longitude":"26.064531554"},{"id":"10691","name":"Calea Plevnei","latitude":"44.44733","longitude":"26.06293"},{"id":"10542","name":"Pod Grozavesti","latitude":"44.44249","longitude":"26.06034"},{"id":"10543","name":"Bd. Iuliu Maniu","latitude":"44.43475","longitude":"26.05436"},{"id":"10544","name":"Bd.Timisoara","latitude":"44.42901","longitude":"26.05445"},{"id":"10643","name":"Sibiu","latitude":"44.42836","longitude":"26.04886"},{"id":"10644","name":"Sergent Moise","latitude":"44.428","longitude":"26.03995"},{"id":"10645","name":"Brasov","latitude":"44.4273","longitude":"26.03216"},{"id":"10646","name":"Compasului","latitude":"44.42708","longitude":"26.02932"},{"id":"10647","name":"Romancierilor","latitude":"44.42658","longitude":"26.02334"},{"id":"10648","name":"Frigocom","latitude":"44.42613","longitude":"26.01739"},{"id":"10649","name":"Valea Oltului","latitude":"44.4247338611","longitude":"26.0122070206"},{"id":"10650","name":"Radox","latitude":"44.42424","longitude":"26.00604"},{"id":"10651","name":"Comautosport","latitude":"44.42374","longitude":"25.99997"},{"id":"10652","name":"C.F.R. Cotroceni","latitude":"44.42816","longitude":"26.00155"},{"id":"10653","name":"Cesarom","latitude":"44.43154","longitude":"26.00063"},{"id":"10654","name":"Urbis","latitude":"44.43096","longitude":"25.99389"},{"id":"10655","name":"S.C. Vest","latitude":"44.43058","longitude":"25.98924"},{"id":"10656","name":"Inscut","latitude":"44.43007","longitude":"25.98308"},{"id":"10657","name":"Depoul Militari","latitude":"44.42955","longitude":"25.97742"}]}]}